FPGA/cpu_core.sv
module cpu_core (
    input  logic        clk,
    input  logic        reset,
    output logic [15:0] pc
);

    /* ========= memories ========= */

    logic [7:0]  imem [0:65535];
    logic [15:0] dmem [0:65535];

    /* ========= registers ========= */

    logic [7:0]  ir;
    logic [15:0] regA;
    logic        ZF, NF;
    logic        halted;

    /* ========= instruction fetch / execute ========= */

    always_ff @(posedge clk) begin
        if (reset) begin
            pc     <= 16'h0000;
            regA  <= 16'h0000;
            ZF    <= 1'b0;
            NF    <= 1'b0;
            halted <= 1'b0;
        end
        else if (!halted) begin
            ir <= imem[pc];

            case (ir)

            8'h10: begin // LDW #imm
                regA <= {imem[pc+1], imem[pc+2]};
                pc   <= pc + 3;
            end

            8'h20: begin // ADDW #imm
                regA <= regA + {imem[pc+1], imem[pc+2]};
                pc   <= pc + 3;
            end

            8'h30: begin // STW addr
                dmem[{imem[pc+1], imem[pc+2]}] <= regA;
                pc <= pc + 3;
            end

            8'h42: begin // JMP addr
                pc <= {imem[pc+1], imem[pc+2]};
            end

            8'hFF: begin // HALT
                halted <= 1'b1;
                pc <= pc;
            end

            default: begin
                pc <= pc + 1;
            end
            endcase

            /* flags */
            ZF <= (regA == 16'h0000);
            NF <= regA[15];
        end
    end

endmodule

isa/v1.0/fpga/tb_cpu.sv
module tb_cpu;

    logic clk = 0;
    logic reset = 1;
    logic [15:0] pc;

    cpu_core dut (
        .clk(clk),
        .reset(reset),
        .pc(pc)
    );

    always #5 clk = ~clk;

    initial begin
        #20 reset = 0;
        #500 $finish;
    end

    initial begin
        $dumpfile("cpu.vcd");
        $dumpvars(0, dut);
    end

endmodule

FPGA/cpu.vcd
$date
	Sun Jan 11 15:44:00 2026
$end
$version
	Icarus Verilog
$end
$timescale
	1s
$end
$scope module tb_cpu $end
$scope module dut $end
$var wire 1 ! clk $end
$var wire 1 " reset $end
$var reg 1 # NF $end
$var reg 1 $ ZF $end
$var reg 1 % halted $end
$var reg 8 & ir [7:0] $end
$var reg 16 ' pc [15:0] $end
$var reg 16 ( regA [15:0] $end
$upscope $end
$upscope $end
$enddefinitions $end
#0
$dumpvars
bx (
bx '
bx &
x%
x$
x#
1"
0!
$end
#5
0%
0#
0$
b0 (
b0 '
1!
#10
0!
#15
1!
#20
0!
0"
#25
1$
b1 '
1!
#30
0!
#35
b10 '
1!
#40
0!
#45
b11 '
1!
#50
0!
#55
b100 '
1!
#60
0!
#65
b101 '
1!
#70
0!
#75
b110 '
1!
#80
0!
#85
b111 '
1!
#90
0!
#95
b1000 '
1!
#100
0!
#105
b1001 '
1!
#110
0!
#115
b1010 '
1!
#120
0!
#125
b1011 '
1!
#130
0!
#135
b1100 '
1!
#140
0!
#145
b1101 '
1!
#150
0!
#155
b1110 '
1!
#160
0!
#165
b1111 '
1!
#170
0!
#175
b10000 '
1!
#180
0!
#185
b10001 '
1!
#190
0!
#195
b10010 '
1!
#200
0!
#205
b10011 '
1!
#210
0!
#215
b10100 '
1!
#220
0!
#225
b10101 '
1!
#230
0!
#235
b10110 '
1!
#240
0!
#245
b10111 '
1!
#250
0!
#255
b11000 '
1!
#260
0!
#265
b11001 '
1!
#270
0!
#275
b11010 '
1!
#280
0!
#285
b11011 '
1!
#290
0!
#295
b11100 '
1!
#300
0!
#305
b11101 '
1!
#310
0!
#315
b11110 '
1!
#320
0!
#325
b11111 '
1!
#330
0!
#335
b100000 '
1!
#340
0!
#345
b100001 '
1!
#350
0!
#355
b100010 '
1!
#360
0!
#365
b100011 '
1!
#370
0!
#375
b100100 '
1!
#380
0!
#385
b100101 '
1!
#390
0!
#395
b100110 '
1!
#400
0!
#405
b100111 '
1!
#410
0!
#415
b101000 '
1!
#420
0!
#425
b101001 '
1!
#430
0!
#435
b101010 '
1!
#440
0!
#445
b101011 '
1!
#450
0!
#455
b101100 '
1!
#460
0!
#465
b101101 '
1!
#470
0!
#475
b101110 '
1!
#480
0!
#485
b101111 '
1!
#490
0!
#495
b110000 '
1!
#500
0!
#505
b110001 '
1!
#510
0!
#515
b110010 '
1!
